[
    {
        "name": "Point 1",
        "lng": "17.9736328125",
        "lat": "59.64554025144323"
    },
    {
        "name": "Point 2",
        "lng": "16.259765625",
        "lat": "60.780618803458935"
    },
    {
        "name": "Point 3",
        "lng": "14.8095703125",
        "lat": "58.47072082411973"
    },
    {
        "name": "Point 4",
        "lng": "17.0947265625",
        "lat": "63.724183392123315"
    },
    {
        "name": "Point 5",
        "lng": "16.435546875",
        "lat": "59.88893689676585"
    },
    {
        "name": "Point 6",
        "lng": "16.962890625",
        "lat": "59.66774058164963"
    },
    {
        "name": "Point 7",
        "lng": "16.5234375",
        "lat": "59.22093407615045"
    },
    {
        "name": "Point 8",
        "lng": "15.908203125",
        "lat": "57.72761921621492"
    },
    {
        "name": "Point 9",
        "lng": "12.65625",
        "lat": "57.32652122521709"
    },
    {
        "name": "Point 10",
        "lng": "13.271484375",
        "lat": "56.96893619436121"
    },
    {
        "name": "Point 11",
        "lng": "13.6669921875",
        "lat": "56.70450561416937"
    },
    {
        "name": "Point 12",
        "lng": "13.6669921875",
        "lat": "55.99838095535963"
    },
    {
        "name": "Point 13",
        "lng": "13.0078125",
        "lat": "56.8249328650072"
    },
    {
        "name": "Point 14",
        "lng": "13.798828125",
        "lat": "58.07787626787517"
    },
    {
        "name": "Point 15",
        "lng": "17.3583984375",
        "lat": "59.06315402462662"
    },
    {
        "name": "Point 16",
        "lng": "18.369140625",
        "lat": "59.734253447591364"
    },
    {
        "name": "Point 17",
        "lng": "20.2587890625",
        "lat": "66.5482634621744"
    },
    {
        "name": "Point 18",
        "lng": "20.1708984375",
        "lat": "65.87472467098549"
    },
    {
        "name": "Point 19",
        "lng": "21.3134765625",
        "lat": "65.5129625532949"
    },
    {
        "name": "Point 20",
        "lng": "19.775390625",
        "lat": "63.95667333648766"
    },
    {
        "name": "Point 21",
        "lng": "18.3251953125",
        "lat": "59.33318942659219"
    },
    {
        "name": "Point 22",
        "lng": "18.28125",
        "lat": "57.633639928856965"
    },
    {
        "name": "Point 23",
        "lng": "18.4130859375",
        "lat": "57.37393841871411"
    },
    {
        "name": "Point 24",
        "lng": "18.4130859375",
        "lat": "57.37393841871411"
    },
    {
        "name": "Point 25",
        "lng": "15.3369140625",
        "lat": "56.29215668507645"
    },
    {
        "name": "Point 26",
        "lng": "9.6240234375",
        "lat": "55.89995614406812"
    },
    {
        "name": "Point 27",
        "lng": "0.0439453125",
        "lat": "51.590722643120145"
    },
    {
        "name": "Point 28",
        "lng": "-2.63671875",
        "lat": "51.6180165487737"
    },
    {
        "name": "Point 29",
        "lng": "-1.40625",
        "lat": "53.25206880589411"
    },
    {
        "name": "Point 30",
        "lng": "-3.1640625",
        "lat": "53.199451902831555"
    },
    {
        "name": "Point 31",
        "lng": "14.6337890625",
        "lat": "60.19615576604439"
    },
    {
        "name": "Point 32",
        "lng": "15.205078125",
        "lat": "59.866883195210214"
    },
    {
        "name": "Point 33",
        "lng": "15.64453125",
        "lat": "62.492027730426905"
    },
    {
        "name": "Point 34",
        "lng": "16.8310546875",
        "lat": "62.83508901142282"
    },
    {
        "name": "Point 35",
        "lng": "15.7763671875",
        "lat": "63.03503931552975"
    },
    {
        "name": "Point 36",
        "lng": "16.1279296875",
        "lat": "62.85514553774182"
    },
    {
        "name": "Point 37",
        "lng": "15.9521484375",
        "lat": "62.57310578449978"
    },
    {
        "name": "Point 38",
        "lng": "15.556640625",
        "lat": "62.04213770379758"
    },
    {
        "name": "Point 39",
        "lng": "17.75390625",
        "lat": "59.26588062825809"
    },
    {
        "name": "Point 40",
        "lng": "17.75390625",
        "lat": "59.26588062825809"
    },
    {
        "name": "Point 41",
        "lng": "16.962890625",
        "lat": "60.4788788301667"
    },
    {
        "name": "Point 42",
        "lng": "16.962890625",
        "lat": "60.4788788301667"
    },
    {
        "name": "Point 43",
        "lng": "16.259765625",
        "lat": "60.780618803458935"
    },
    {
        "name": "Point 44",
        "lng": "16.259765625",
        "lat": "60.780618803458935"
    },
    {
        "name": "Point 45",
        "lng": "15.6005859375",
        "lat": "60.80206374467983"
    },
    {
        "name": "Point 46",
        "lng": "15.6005859375",
        "lat": "60.80206374467983"
    },
    {
        "name": "Point 47",
        "lng": "15.732421875",
        "lat": "60.60854176060904"
    },
    {
        "name": "Point 48",
        "lng": "14.3701171875",
        "lat": "56.92099675839104"
    },
    {
        "name": "Point 49",
        "lng": "13.1396484375",
        "lat": "55.94919982336744"
    },
    {
        "name": "Point 50",
        "lng": "13.1396484375",
        "lat": "55.94919982336744"
    },
    {
        "name": "Point 51",
        "lng": "14.1943359375",
        "lat": "56.29215668507645"
    },
    {
        "name": "Point 52",
        "lng": "13.271484375",
        "lat": "56.96893619436121"
    },
    {
        "name": "Point 53",
        "lng": "17.4462890625",
        "lat": "60.43554230669233"
    },
    {
        "name": "Point 54",
        "lng": "17.4462890625",
        "lat": "60.28340847828243"
    },
    {
        "name": "Point 55",
        "lng": "15.8203125",
        "lat": "59.866883195210214"
    },
    {
        "name": "Point 56",
        "lng": "17.3583984375",
        "lat": "59.06315402462662"
    },
    {
        "name": "Point 57",
        "lng": "16.8310546875",
        "lat": "59.06315402462662"
    },
    {
        "name": "Point 58",
        "lng": "17.05078125",
        "lat": "58.859223547066584"
    },
    {
        "name": "Point 59",
        "lng": "16.083984375",
        "lat": "59.489726035537075"
    },
    {
        "name": "Point 60",
        "lng": "13.4033203125",
        "lat": "57.9148477670092"
    },
    {
        "name": "Point 61",
        "lng": "20.126953125",
        "lat": "64.35893097894458"
    },
    {
        "name": "Point 62",
        "lng": "18.896484375",
        "lat": "64.64270382119372"
    },
    {
        "name": "Point 63",
        "lng": "20.2587890625",
        "lat": "66.5482634621744"
    },
    {
        "name": "Point 64",
        "lng": "21.3134765625",
        "lat": "65.5129625532949"
    },
    {
        "name": "Point 65",
        "lng": "21.4453125",
        "lat": "65.38514722188854"
    },
    {
        "name": "Point 66",
        "lng": "17.6220703125",
        "lat": "59.877911874831156"
    },
    {
        "name": "Point 67",
        "lng": "18.10546875",
        "lat": "59.31076795603884"
    },
    {
        "name": "Point 68",
        "lng": "18.0615234375",
        "lat": "59.15340309205037"
    },
    {
        "name": "Point 69",
        "lng": "17.841796875",
        "lat": "59.130863097255904"
    },
    {
        "name": "Point 70",
        "lng": "17.611083984375",
        "lat": "59.76746035005358"
    },
    {
        "name": "Point 71",
        "lng": "17.852783203125",
        "lat": "59.92199002450385"
    },
    {
        "name": "Point 72",
        "lng": "17.720947265625",
        "lat": "59.6954703349364"
    },
    {
        "name": "Point 73",
        "lng": "17.4462890625",
        "lat": "59.833775202184206"
    },
    {
        "name": "Point 74",
        "lng": "17.8857421875",
        "lat": "59.86136748351594"
    },
    {
        "name": "Point 75",
        "lng": "18.3251953125",
        "lat": "59.23217626921806"
    },
    {
        "name": "Point 76",
        "lng": "18.160400390625",
        "lat": "59.55102479512502"
    },
    {
        "name": "Point 77",
        "lng": "18.489990234375",
        "lat": "59.472988847741355"
    },
    {
        "name": "Point 78",
        "lng": "18.78662109375",
        "lat": "59.89995826181929"
    },
    {
        "name": "Point 79",
        "lng": "16.556396484375",
        "lat": "59.61221219518693"
    },
    {
        "name": "Point 80",
        "lng": "16.929931640625",
        "lat": "58.78528524510292"
    },
    {
        "name": "Point 81",
        "lng": "15.84228515625",
        "lat": "59.37239142233717"
    },
    {
        "name": "Point 82",
        "lng": "15.194091796875",
        "lat": "59.28833169203345"
    },
    {
        "name": "Point 83",
        "lng": "16.907958984375",
        "lat": "59.46740794183742"
    },
    {
        "name": "Point 84",
        "lng": "18.885498046875",
        "lat": "59.75086102411168"
    },
    {
        "name": "Point 85",
        "lng": "13.018798828125",
        "lat": "55.5969712679851"
    },
    {
        "name": "Point 86",
        "lng": "12.777099609375",
        "lat": "56.05976947910657"
    },
    {
        "name": "Point 87",
        "lng": "12.5244140625",
        "lat": "56.92099675839104"
    },
    {
        "name": "Point 88",
        "lng": "13.33740234375",
        "lat": "55.63419794625838"
    },
    {
        "name": "Point 89",
        "lng": "12.98583984375",
        "lat": "55.90611502601163"
    },
    {
        "name": "Point 90",
        "lng": "17.75390625",
        "lat": "59.02924933736395"
    },
    {
        "name": "Point 91",
        "lng": "13.238525390625",
        "lat": "55.85681658243853"
    },
    {
        "name": "Point 92",
        "lng": "17.75390625",
        "lat": "59.56215805601119"
    },
    {
        "name": "Point 93",
        "lng": "17.984619140625",
        "lat": "59.539887852931486"
    },
    {
        "name": "Point 94",
        "lng": "11.942138671875",
        "lat": "57.70414723434193"
    },
    {
        "name": "Point 95",
        "lng": "12.32666015625",
        "lat": "57.81550367239279"
    },
    {
        "name": "Point 96",
        "lng": "12.030029296875",
        "lat": "58.025555184126034"
    },
    {
        "name": "Point 97",
        "lng": "12.10693359375",
        "lat": "57.903174456371474"
    },
    {
        "name": "Point 98",
        "lng": "12.0849609375",
        "lat": "57.58066944459514"
    },
    {
        "name": "Point 99",
        "lng": "13.24951171875",
        "lat": "55.547280698640805"
    },
    {
        "name": "Point 100",
        "lng": "4.921875",
        "lat": "52.348763181988105"
    },
    {
        "name": "Point 101",
        "lng": "13.447265625",
        "lat": "52.50953477032727"
    },
    {
        "name": "Point 102",
        "lng": "2.4169921875",
        "lat": "48.80686346108517"
    },
    {
        "name": "Point 103",
        "lng": "13.8427734375",
        "lat": "51.53608560178475"
    },
    {
        "name": "Point 104",
        "lng": "8.3935546875",
        "lat": "52.93539665862318"
    },
    {
        "name": "Point 105",
        "lng": "10.0634765625",
        "lat": "53.64463782485651"
    },
    {
        "name": "Point 106",
        "lng": "10.1513671875",
        "lat": "55.35413531021057"
    },
    {
        "name": "Point 107",
        "lng": "-6.85546875",
        "lat": "53.4357192066942"
    },
    {
        "name": "Point 108",
        "lng": "8.701171875",
        "lat": "47.30903424774781"
    },
    {
        "name": "Point 109",
        "lng": "19.5556640625",
        "lat": "53.54030739150019"
    },
    {
        "name": "Point 110",
        "lng": "18.896484375",
        "lat": "47.517200697839414"
    },
    {
        "name": "Point 111",
        "lng": "-3.0322265625",
        "lat": "55.88763544617004"
    },
    {
        "name": "Point 112",
        "lng": "-1.51611328125",
        "lat": "54.92714186454645"
    },
    {
        "name": "Point 113",
        "lng": "-4.24072265625",
        "lat": "57.35023747739682"
    },
    {
        "name": "Point 114",
        "lng": "12.23876953125",
        "lat": "55.727110085045986"
    },
    {
        "name": "Point 115",
        "lng": "12.2607421875",
        "lat": "55.640398956687335"
    },
    {
        "name": "Point 116",
        "lng": "12.54638671875",
        "lat": "55.71473455012689"
    },
    {
        "name": "Point 117",
        "lng": "14.7216796875",
        "lat": "56.92099675839104"
    },
    {
        "name": "Point 118",
        "lng": "14.23828125",
        "lat": "57.70414723434193"
    }
]